pstat_simpledb-0.0.1.data/data/LICENSE
simpledb/__init__.py
simpledb/config.py
simpledb/models.py
simpledb/simpledb.py
pstat_simpledb-0.0.1.dist-info/LICENSE
pstat_simpledb-0.0.1.dist-info/METADATA
pstat_simpledb-0.0.1.dist-info/WHEEL
pstat_simpledb-0.0.1.dist-info/top_level.txt
pstat_simpledb-0.0.1.dist-info/RECORD
